ai_ml_sdk_model_converter-0.8.0.data/purelib/model_converter/__init__.py
ai_ml_sdk_model_converter-0.8.0.data/purelib/model_converter/cli.py
ai_ml_sdk_model_converter-0.8.0.data/purelib/model_converter/binaries/bin/model-converter.exe
ai_ml_sdk_model_converter-0.8.0.data/purelib/model_converter/binaries/lib/ai-ml-sdk-model-converter.spdx.json
ai_ml_sdk_model_converter-0.8.0.data/purelib/model_converter/binaries/lib/cmake/ModelConverter/ModelConverterConfig-debug.cmake
ai_ml_sdk_model_converter-0.8.0.data/purelib/model_converter/binaries/lib/cmake/ModelConverter/ModelConverterConfig-release.cmake
ai_ml_sdk_model_converter-0.8.0.data/purelib/model_converter/binaries/lib/cmake/ModelConverter/ModelConverterConfig.cmake
ai_ml_sdk_model_converter-0.8.0.data/purelib/model_converter/binaries/lib/cmake/ModelConverter/ModelConverterConfigVersion.cmake
ai_ml_sdk_model_converter-0.8.0.dist-info/METADATA
ai_ml_sdk_model_converter-0.8.0.dist-info/WHEEL
ai_ml_sdk_model_converter-0.8.0.dist-info/entry_points.txt
ai_ml_sdk_model_converter-0.8.0.dist-info/top_level.txt
ai_ml_sdk_model_converter-0.8.0.dist-info/RECORD
