Metadata-Version: 2.4
Name: ai_ml_sdk_model_converter
Version: 0.8.0
Summary: ML SDK Model Converter
